src/__init__.py
src/extractor.py
src/kube_init.py
src/kubernetes_utils.py
src/main.py
src/registries.py
src/transformer_tf.py
src/utils.py
src/yaml_transformer.py
k8s_to_azure_container_app-0.1.0.dist-info/LICENSE
k8s_to_azure_container_app-0.1.0.dist-info/METADATA
k8s_to_azure_container_app-0.1.0.dist-info/WHEEL
k8s_to_azure_container_app-0.1.0.dist-info/entry_points.txt
k8s_to_azure_container_app-0.1.0.dist-info/top_level.txt
k8s_to_azure_container_app-0.1.0.dist-info/RECORD
