Metadata-Version: 2.1
Name: k8s-to-azure-container-app
Version: 0.1.0
Summary: Migrate Kubernetes deployments into Azure Container Apps
Home-page: https://github.com/xente/K8sToAzureContainerApp
Requires-Python: >=3.6
License-File: LICENSE
Requires-Dist: pyyaml >=6.0.1
Requires-Dist: kubernetes >=29.0.0
